CHANGELOG.txt
LICENSE.txt
MANIFEST.in
README.md
setup.py
Cython_GLDA/GLDA.py
Cython_GLDA/__init__.py
Cython_GLDA.egg-info/PKG-INFO
Cython_GLDA.egg-info/SOURCES.txt
Cython_GLDA.egg-info/dependency_links.txt
Cython_GLDA.egg-info/top_level.txt
Cython_GLDA/cython_trainer/_cython_trainer.c
Cython_GLDA/cython_trainer/_cython_utils.c
Cython_GLDA/cython_trainer/__init__.py
Cython_GLDA/test/__init__.py
Cython_GLDA/test/test.py